jsonparserdf.py
jsonparserdf-0.0.1.dist-info/LICENSE.txt
jsonparserdf-0.0.1.dist-info/METADATA
jsonparserdf-0.0.1.dist-info/WHEEL
jsonparserdf-0.0.1.dist-info/top_level.txt
jsonparserdf-0.0.1.dist-info/RECORD
