Metadata-Version: 2.1
Name: jsonparserdf
Version: 0.0.1
Summary: Process json and convert it into dataframes
Home-page: https://github.com/NabeelZaidi
Author: Nabeel Zaidi
Author-email: nabeel.zaidi@lyftron.com
License: UNKNOWN
Platform: UNKNOWN
Requires-Dist: pandas (~=1.1.3)
Requires-Dist: XlsxWriter (~=1.3.7)
